README.md
setup.cfg
setup.py
tap_eloqua/__init__.py
tap_eloqua/client.py
tap_eloqua/discover.py
tap_eloqua/schema.py
tap_eloqua/sync.py
tap_eloqua.egg-info/PKG-INFO
tap_eloqua.egg-info/SOURCES.txt
tap_eloqua.egg-info/dependency_links.txt
tap_eloqua.egg-info/entry_points.txt
tap_eloqua.egg-info/requires.txt
tap_eloqua.egg-info/top_level.txt
tap_eloqua/schemas/assets.json
tap_eloqua/schemas/campaigns.json
tap_eloqua/schemas/emailGroups.json
tap_eloqua/schemas/emails.json
tap_eloqua/schemas/forms.json
tap_eloqua/schemas/visitors.json