Metadata-Version: 2.1
Name: tap-eloqua
Version: 1.3.0
Summary: Singer.io tap for extracting data from the Oracle Eloqua API
Home-page: https://singer.io
Author: Stitch
License: UNKNOWN
Platform: UNKNOWN
Classifier: Programming Language :: Python :: 3 :: Only
Provides-Extra: dev
